setup.py
iynaefi_distributions/Binomialdistribution.py
iynaefi_distributions/Gaussiandistribution.py
iynaefi_distributions/Generaldistribution.py
iynaefi_distributions/__init__.py
iynaefi_distributions.egg-info/PKG-INFO
iynaefi_distributions.egg-info/SOURCES.txt
iynaefi_distributions.egg-info/dependency_links.txt
iynaefi_distributions.egg-info/not-zip-safe
iynaefi_distributions.egg-info/top_level.txt