Metadata-Version: 1.0
Name: iynaefi-distributions
Version: 0.1
Summary: Gaussian distributions
Home-page: UNKNOWN
Author: Ifeanyi Eze
Author-email: ezeifeanyic@gmail.com
License: UNKNOWN
Platform: UNKNOWN
